trame/__init__.py
trame/modules/__init__.py
trame/modules/rca.py
trame/widgets/__init__.py
trame/widgets/rca.py
trame_rca/__init__.py
trame_rca/protocol.py
trame_rca/utils.py
trame_rca/vtk_utils.py
trame_rca/encoders/__init__.py
trame_rca/encoders/img.py
trame_rca/encoders/pil.py
trame_rca/encoders/turbo_jpeg.py
trame_rca/module/__init__.py
trame_rca/module/serve/trame-rca.umd.js
trame_rca/widgets/__init__.py
trame_rca/widgets/rca.py
trame_rca-2.2.3.dist-info/licenses/LICENSE
trame_rca-2.2.3.dist-info/METADATA
trame_rca-2.2.3.dist-info/WHEEL
trame_rca-2.2.3.dist-info/top_level.txt
trame_rca-2.2.3.dist-info/RECORD
